codestream/__init__.py
codestream-0.1.2.dist-info/METADATA
codestream-0.1.2.dist-info/WHEEL
codestream-0.1.2.dist-info/entry_points.txt
codestream-0.1.2.dist-info/RECORD
