Metadata-Version: 2.4
Name: codestream
Version: 0.1.2
Summary: stream your codebase like an llm
Author-email: Aaron Glover <aglove2189@gmail.com>
Requires-Python: >=3.13
Requires-Dist: gitpython>=3.1.0
Requires-Dist: pygments>=2.19.1
Requires-Dist: rich>=14.0.0
